LICENSE.txt
MANIFEST.in
README.md
VERSION
setup.cfg
setup.py
./deepracer_env_config/__init__.py
./deepracer_env_config/client.py
./deepracer_env_config/config_server.py
./deepracer_env_config/constants.py
./deepracer_env_config/configs/__init__.py
./deepracer_env_config/configs/agent.py
./deepracer_env_config/configs/area.py
./deepracer_env_config/configs/behaviour.py
./deepracer_env_config/configs/config_interface.py
./deepracer_env_config/configs/location.py
./deepracer_env_config/configs/track.py
deepracer_env_config.egg-info/PKG-INFO
deepracer_env_config.egg-info/SOURCES.txt
deepracer_env_config.egg-info/dependency_links.txt
deepracer_env_config.egg-info/requires.txt
deepracer_env_config.egg-info/top_level.txt
test/test_deepracer_env_config_import.py